Workbook

Sheet Dashboard
A1: Online Retail Advanced Analytics Dashboard
D3: Key findings
A4: Source rows | B4: =Data_Profile!B4 -> 541909 | D4: Missing CustomerID affects customer-level KPI segmentation; its associated valid-sales revenue is about 16.5% of sales revenue.
A5: Missing CustomerID | B5: =Data_Profile!B5 -> 135080 | D5: Peak activity with below-median AOV occurs mainly from 11:00–14:00. This is a monetization/traffic proxy because visitor/session data is not present.
A6: Missing Description | B6: =Data_Profile!B6 -> 1454 | D6: Top 20% of products contribute 79.9% of revenue.
A7: Valid sales rows | B7: =Data_Profile!B7 -> 530104 | D7: Bottom 20% contribute 0.21% of revenue. No cost field exists, so actual profit-margin dilution cannot be proven.
A8: Sales revenue | B8: =Data_Profile!C7 -> 10666685 | D8: Forecast for the next quarter using quarterly seasonality + deseasonalized linear trend: £2,692,926.
A9: Distinct orders | B9: =Data_Profile!D7 -> 19960
A10: AOV | B10: =B8/B9 -> 534.40303
A11: Missing CustomerID revenue | B11: =Data_Profile!C5 -> 1755276.6
A12: Missing CustomerID revenue share | B12: =B11/B8 -> 0.16455691
A13: Top 20% revenue share | B13: =Pareto_Analysis!K8 -> 0.79888897
A14: Bottom 20% revenue share | B14: =Pareto_Analysis!K10 -> 0.0021417351
A15: Next-quarter forecast | B15: =TimeSeries_Forecast!J6 -> 2692926.2

Sheet Data_Profile
A1: Power Query Data Profiling — Missing Values & KPI Impact
A3: Metric | B3: Rows | C3: Revenue | D3: Orders | E3: Impact
A4: Total source rows | B4: 541909 | C4: 10666685 | D4: 19960 | E4: Dataset size.
A5: Missing CustomerID | B5: 135080 | C5: 1755276.6 | D5: 1428 | E5: Customer-level segmentation and customer KPI accuracy are affected.
A6: Missing Description | B6: 1454 | C6: 0 | D6: 0 | E6: Product-description completeness is affected; these rows contribute £0 revenue in this file.
A7: Valid sales rows | B7: 530104 | C7: 10666685 | D7: 19960 | E7: Used for AOV, hourly, Pareto and time-series calculations.
A9: CustomerID missing % | B9: =B5/B4 -> 0.24926694
A10: Description missing % | B10: =B6/B4 -> 0.0026831073
A11: Missing CustomerID revenue share | B11: =C5/C4 -> 0.16455691
A12: Missing Description revenue share | B12: =C6/C4 -> 0
A15: Power Query M — profiling
A16: let Source = Excel.Workbook(File.Contents("<PATH_TO_OnlineRetail_Raw_Source.xlsx>"), null, true), Raw = Source{[Item="OnlineRetail_Raw",Kind="Sheet"]}[Data], PromotedHeaders = Table.PromoteHeaders(Raw, [PromoteAllScalars=true]), ChangedTypes = Table.TransformColumnTypes(PromotedHeaders,{ {"InvoiceNo", type text},{"StockCode", type text},{"Description", type text}, {"Quantity", Int64.Type},{"InvoiceDate", type datetime},{"UnitPrice", type number}, {"CustomerID", Int64.Type},{"Country", type text} }), AddCustomerMissing = Table.AddColumn(ChangedTypes,"CustomerID_Missing",each if [CustomerID]=null then 1 else 0,Int64.Type), AddDescriptionMissing = Table.AddColumn(AddCustomerMissing,"Description_Missing",each if [Description]=null then 1 else 0,Int64.Type), Result = #table({"Metric","Value"},{ {"Rows",Table.RowCount(AddDescriptionMissing)}, {"Missing CustomerID",List.Sum(AddDescriptionMissing[CustomerID_Missing])}, {"Missing Description",List.Sum(AddDescriptionMissing[Description_Missing])} }) in Result
A20: Power Query M — clean sales table
A21: let Source = Excel.Workbook(File.Contents("<PATH_TO_OnlineRetail_Raw_Source.xlsx>"), null, true), Raw = Source{[Item="OnlineRetail_Raw",Kind="Sheet"]}[Data], PromotedHeaders = Table.PromoteHeaders(Raw, [PromoteAllScalars=true]), ChangedTypes = Table.TransformColumnTypes(PromotedHeaders,{ {"InvoiceNo", type text},{"StockCode", type text},{"Description", type text}, {"Quantity", Int64.Type},{"InvoiceDate", type datetime},{"UnitPrice", type number}, {"CustomerID", Int64.Type},{"Country", type text} }), FilterSales = Table.SelectRows(ChangedTypes, each [Quantity] > 0 and [UnitPrice] > 0 and not Text.StartsWith([InvoiceNo],"C")), AddRevenue = Table.AddColumn(FilterSales,"Revenue",each [Quantity]*[UnitPrice],type number), AddHour = Table.AddColumn(AddRevenue,"Hour",each Time.Hour(Time.From([InvoiceDate])),Int64.Type), AddMinute = Table.AddColumn(AddHour,"Minute",each Time.Minute(Time.From([InvoiceDate])),Int64.Type) in AddMinute

Sheet Hourly_Pivot_AOV
A1: Multi-layered Pivot-style Hourly Analysis — AOV & Revenue per Minute
A3: Hour | B3: Revenue | C3: Orders | D3: Customers | E3: AOV | F3: Orders/Minute | G3: Revenue/Minute | H3: Customer Coverage | I3: Review Flag
A4: 6 | B4: 4.25 | C4: 1 | D4: 1 | E4: =B4/C4 -> 4.25 | F4: =C4/60 -> 0.016666667 | G4: =B4/60 -> 0.070833333 | H4: =D4/C4 -> 1 | I4: =IF(AND(F4>=MEDIAN($F$4:$F$21),E4<MEDIAN($E$4:$E$21)),"Review","Normal") -> Normal
A5: 7 | B5: 31059.21 | C5: 29 | D5: 28 | E5: =B5/C5 -> 1071.0072 | F5: =C5/60 -> 0.48333333 | G5: =B5/60 -> 517.6535 | H5: =D5/C5 -> 0.96551724 | I5: =IF(AND(F5>=MEDIAN($F$4:$F$21),E5<MEDIAN($E$4:$E$21)),"Review","Normal") -> Normal
A6: 8 | B6: 283868.52 | C6: 566 | D6: 427 | E6: =B6/C6 -> 501.53449 | F6: =C6/60 -> 9.4333333 | G6: =B6/60 -> 4731.142 | H6: =D6/C6 -> 0.75441696 | I6: =IF(AND(F6>=MEDIAN($F$4:$F$21),E6<MEDIAN($E$4:$E$21)),"Review","Normal") -> Normal
A7: 9 | B7: 990267.82 | C7: 1484 | D7: 890 | E7: =B7/C7 -> 667.29638 | F7: =C7/60 -> 24.733333 | G7: =B7/60 -> 16504.464 | H7: =D7/C7 -> 0.59973046 | I7: =IF(AND(F7>=MEDIAN($F$4:$F$21),E7<MEDIAN($E$4:$E$21)),"Review","Normal") -> Normal
A8: 10 | B8: 1446742.7 | C8: 2361 | D8: 1268 | E8: =B8/C8 -> 612.76692 | F8: =C8/60 -> 39.35 | G8: =B8/60 -> 24112.378 | H8: =D8/C8 -> 0.53706057 | I8: =IF(AND(F8>=MEDIAN($F$4:$F$21),E8<MEDIAN($E$4:$E$21)),"Review","Normal") -> Normal
A9: 11 | B9: 1239954.4 | C9: 2396 | D9: 1303 | E9: =B9/C9 -> 517.5102 | F9: =C9/60 -> 39.933333 | G9: =B9/60 -> 20665.907 | H9: =D9/C9 -> 0.54382304 | I9: =IF(AND(F9>=MEDIAN($F$4:$F$21),E9<MEDIAN($E$4:$E$21)),"Review","Normal") -> Review
A10: 12 | B10: 1444245.9 | C10: 3220 | D10: 1637 | E10: =B10/C10 -> 448.52357 | F10: =C10/60 -> 53.666667 | G10: =B10/60 -> 24070.765 | H10: =D10/C10 -> 0.50838509 | I10: =IF(AND(F10>=MEDIAN($F$4:$F$21),E10<MEDIAN($E$4:$E$21)),"Review","Normal") -> Review
A11: 13 | B11: 1265736.3 | C11: 2753 | D11: 1573 | E11: =B11/C11 -> 459.76618 | F11: =C11/60 -> 45.883333 | G11: =B11/60 -> 21095.605 | H11: =D11/C11 -> 0.57137668 | I11: =IF(AND(F11>=MEDIAN($F$4:$F$21),E11<MEDIAN($E$4:$E$21)),"Review","Normal") -> Review
A12: 14 | B12: 1181812.4 | C12: 2457 | D12: 1386 | E12: =B12/C12 -> 480.99812 | F12: =C12/60 -> 40.95 | G12: =B12/60 -> 19696.873 | H12: =D12/C12 -> 0.56410256 | I12: =IF(AND(F12>=MEDIAN($F$4:$F$21),E12<MEDIAN($E$4:$E$21)),"Review","Normal") -> Review
A13: 15 | B13: 1352972.2 | C13: 2336 | D13: 1275 | E13: =B13/C13 -> 579.1833 | F13: =C13/60 -> 38.933333 | G13: =B13/60 -> 22549.536 | H13: =D13/C13 -> 0.54580479 | I13: =IF(AND(F13>=MEDIAN($F$4:$F$21),E13<MEDIAN($E$4:$E$21)),"Review","Normal") -> Normal
A14: 16 | B14: 754006.56 | C14: 1335 | D14: 749 | E14: =B14/C14 -> 564.79892 | F14: =C14/60 -> 22.25 | G14: =B14/60 -> 12566.776 | H14: =D14/C14 -> 0.56104869 | I14: =IF(AND(F14>=MEDIAN($F$4:$F$21),E14<MEDIAN($E$4:$E$21)),"Review","Normal") -> Normal
A15: 17 | B15: 461603.49 | C15: 667 | D15: 414 | E15: =B15/C15 -> 692.05921 | F15: =C15/60 -> 11.116667 | G15: =B15/60 -> 7693.3915 | H15: =D15/C15 -> 0.62068966 | I15: =IF(AND(F15>=MEDIAN($F$4:$F$21),E15<MEDIAN($E$4:$E$21)),"Review","Normal") -> Normal
... A18: 20 | B18: 18932.76 | C18: 18 | D18: 15 | E18: =B18/C18 -> 1051.82 | F18: =C18/60 -> 0.3 | G18: =B18/60 -> 315.546 | H18: =D18/C18 -> 0.83333333 | I18: =IF(AND(F18>=MEDIAN($F$4:$F$21),E18<MEDIAN($E$4:$E$21)),"Review","Normal") -> Normal
A25: Note
A26: True conversion rate requires visits/sessions, which are absent from this dataset. The Review Flag therefore identifies above-median Orders/Minute combined with below-median AOV; it is a practical traffic/monetization proxy, not a true conversion metric.

Sheet Pareto_Analysis
A1: Dynamic Pareto Analysis — 80/20 Revenue Rule
A3: Top/bottom threshold | B3: 0.2 | D3: Top 20% count | E3: =ROUNDUP(COUNTA(C7:C4167)*$B$3,0) -> 833 | G3: Bottom 20% count | H3: =ROUNDUP(COUNTA(C7:C4167)*$B$3,0) -> 833
J5: Summary
A6: Rank | B6: StockCode | C6: Description | D6: Revenue | E6: Units | F6: Orders | G6: Cumulative Revenue | H6: Cumulative % | J6: Total product revenue | K6: =SUM(D7:D4167) -> 10666685
A7: 1 | B7: DOT | C7: DOTCOM POSTAGE | D7: 206248.77 | E7: 706 | F7: 706 | G7: =SUM($D$7:D7) -> 206248.77 | H7: =G7/SUM($D$7:$D$4167) -> 0.01933579 | J7: Top 20% revenue | K7: =SUMIF(A7:A4167,"<="&E3,D7:D4167) -> 8521496.7
A8: 2 | B8: 22423 | C8: REGENCY CAKESTAND 3 TIER | D8: 174484.74 | E8: 13879 | F8: 1988 | G8: =SUM($D$7:D8) -> 380733.51 | H8: =G8/SUM($D$7:$D$4167) -> 0.035693707 | J8: Top 20% revenue share | K8: =K7/K6 -> 0.79888897
A9: 3 | B9: 23843 | C9: PAPER CRAFT , LITTLE BIRDIE | D9: 168469.6 | E9: 80995 | F9: 1 | G9: =SUM($D$7:D9) -> 549203.11 | H9: =G9/SUM($D$7:$D$4167) -> 0.051487705 | J9: Bottom 20% revenue | K9: =SUMIF(A7:A4167,">"&COUNTA(C7:C4167)-H3,D7:D4167) -> 22845.213
A10: 4 | B10: 85123A | C10: WHITE HANGING HEART T-LIGHT HOLDER | D10: 104340.29 | E10: 37599 | F10: 2189 | G10: =SUM($D$7:D10) -> 653543.4 | H10: =G10/SUM($D$7:$D$4167) -> 0.061269591 | J10: Bottom 20% revenue share | K10: =K9/K6 -> 0.0021417351
A11: 5 | B11: 47566 | C11: PARTY BUNTING | D11: 99504.33 | E11: 18295 | F11: 1685 | G11: =SUM($D$7:D11) -> 753047.73 | H11: =G11/SUM($D$7:$D$4167) -> 0.070598106
A12: 6 | B12: 85099B | C12: JUMBO BAG RED RETROSPOT | D12: 94340.05 | E12: 48474 | F12: 2089 | G12: =SUM($D$7:D12) -> 847387.78 | H12: =G12/SUM($D$7:$D$4167) -> 0.079442471 | J12: Interpretation
A13: 7 | B13: 23166 | C13: MEDIUM CERAMIC TOP STORAGE JAR | D13: 81700.92 | E13: 78033 | F13: 247 | G13: =SUM($D$7:D13) -> 929088.7 | H13: =G13/SUM($D$7:$D$4167) -> 0.08710192 | J13: Top 20% of 4,161 products generate about 79.9% of revenue. Bottom 20% generate about 0.21%. The dataset contains no cost/profit field, so margin dilution cannot be proven; use the bottom segment as a low-revenue review list.
A14: 8 | B14: M | C14: Manual | D14: 78110.27 | E14: 7224 | F14: 289 | G14: =SUM($D$7:D14) -> 1007199 | H14: =G14/SUM($D$7:$D$4167) -> 0.094424745
A15: 9 | B15: POST | C15: POSTAGE | D15: 78101.88 | E15: 3150 | F15: 1126 | G15: =SUM($D$7:D15) -> 1085300.9 | H15: =G15/SUM($D$7:$D$4167) -> 0.10174678
A16: 10 | B16: 23084 | C16: RABBIT NIGHT LIGHT | D16: 66964.99 | E16: 30788 | F16: 994 | G16: =SUM($D$7:D16) -> 1152265.8 | H16: =G16/SUM($D$7:$D$4167) -> 0.10802474
A17: 11 | B17: 22086 | C17: PAPER CHAIN KIT 50'S CHRISTMAS | D17: 64952.29 | E17: 19355 | F17: 1160 | G17: =SUM($D$7:D17) -> 1217218.1 | H17: =G17/SUM($D$7:$D$4167) -> 0.11411401
A18: 12 | B18: 84879 | C18: ASSORTED COLOUR BIRD ORNAMENT | D18: 59094.93 | E18: 36461 | F18: 1455 | G18: =SUM($D$7:D18) -> 1276313.1 | H18: =G18/SUM($D$7:$D$4167) -> 0.11965415
A19: 13 | B19: 79321 | C19: CHILLI LIGHTS | D19: 54117.76 | E19: 10306 | F19: 661 | G19: =SUM($D$7:D19) -> 1330430.8 | H19: =G19/SUM($D$7:$D$4167) -> 0.12472768
A20: 14 | B20: 23298 | C20: SPOTTY BUNTING | D20: 42548.13 | E20: 8327 | F20: 1140 | G20: =SUM($D$7:D20) -> 1372978.9 | H20: =G20/SUM($D$7:$D$4167) -> 0.12871656
A21: 15 | B21: 22386 | C21: JUMBO BAG PINK POLKADOT | D21: 42436.24 | E21: 21465 | F21: 1218 | G21: =SUM($D$7:D21) -> 1415415.2 | H21: =G21/SUM($D$7:$D$4167) -> 0.13269495
A22: 16 | B22: 21137 | C22: BLACK RECORD COVER FRAME | D22: 40652.13 | E22: 11656 | F22: 375 | G22: =SUM($D$7:D22) -> 1456067.3 | H22: =G22/SUM($D$7:$D$4167) -> 0.13650608
A23: 17 | B23: 22502 | C23: PICNIC BASKET WICKER 60 PIECES | D23: 39619.5 | E23: 61 | F23: 2 | G23: =SUM($D$7:D23) -> 1495686.8 | H23: =G23/SUM($D$7:$D$4167) -> 0.1402204
A24: 18 | B24: 23284 | C24: DOORMAT KEEP CALM AND COME IN | D24: 38166.64 | E24: 5491 | F24: 728 | G24: =SUM($D$7:D24) -> 1533853.5 | H24: =G24/SUM($D$7:$D$4167) -> 0.14379852
A25: 19 | B25: 22720 | C25: SET OF 3 CAKE TINS PANTRY DESIGN | D25: 38158.39 | E25: 7493 | F25: 1385 | G25: =SUM($D$7:D25) -> 1572011.8 | H25: =G25/SUM($D$7:$D$4167) -> 0.14737586
... A4167: 4161 | B4167: PADS | C4167: PADS TO MATCH ALL CUSHIONS | D4167: 0.003 | E4167: 3 | F4167: 3 | G4167: =SUM($D$7:D4167) -> 10666685 | H4167: =G4167/SUM($D$7:$D$4167) -> 1

Sheet TimeSeries_Forecast
A1: Time-Series Analysis — Seasonal Trend, Variance & Next-Quarter Forecast
A3: Month | B3: Revenue | C3: Time Index | D3: 3M Moving Average | E3: Trend | F3: Variance | G3: Variance % | I3: Forecast method | J3: Quarterly seasonal index + linear trend on deseasonalized revenue
A4: 40179 | B4: 58960.79 | C4: 1 | E4: -142102.62 | F4: 201063.41 | G4: -1.414917
A5: 40210 | B5: 47748.38 | C5: 2 | E5: -91098.461 | F5: 138846.84 | G5: -1.5241404 | I5: Next quarter | J5: 2011Q4 → Q1-2012
A6: 40238 | B6: 46943.71 | C6: 3 | D6: 51217.627 | E6: -40094.304 | F6: 87038.014 | G6: -2.1708324 | I6: Forecast revenue | J6: =FORECAST(9,F34:F41,C34:C41)*AVERAGEIF(D34:D41,1,E34:E41) -> 2692926.2
A7: 40269 | B7: 0 | C7: 4 | D7: 31564.03 | E7: 10909.853 | F7: -10909.853 | G7: -1 | I7: ToolPak reproduction | J7: Use Data → Data Analysis → Regression on the quarterly deseasonalized table (Time Index as X, Deseasonalized Revenue as Y). The resulting trend can be used with the Q1 seasonal index shown above.
A8: 40299 | B8: 31774.95 | C8: 5 | D8: 26239.553 | E8: 61914.011 | F8: -30139.061 | G8: -0.48678902
A9: 40330 | B9: 54830.46 | C9: 6 | D9: 28868.47 | E9: 112918.17 | F9: -58087.708 | G9: -0.51442305
A10: 40360 | B10: 99618.2 | C10: 7 | D10: 62074.537 | E10: 163922.32 | F10: -64304.125 | G10: -0.39228412
A11: 40391 | B11: 45389.98 | C11: 8 | D11: 66612.88 | E11: 214926.48 | F11: -169536.5 | G11: -0.7888116
A12: 40422 | B12: 53586.18 | C12: 9 | D12: 66198.12 | E12: 265930.64 | F12: -212344.46 | G12: -0.79849565
A13: 40452 | B13: 59182.92 | C13: 10 | D13: 52719.693 | E13: 316934.8 | F13: -257751.88 | G13: -0.81326468
A14: 40483 | B14: 0 | C14: 11 | D14: 37589.7 | E14: 367938.95 | F14: -367938.95 | G14: -1
A15: 40513 | B15: 325710.57 | C15: 12 | D15: 128297.83 | E15: 418943.11 | F15: -93232.541 | G15: -0.22254225
A16: 40544 | B16: 702201.27 | C16: 13 | D16: 342637.28 | E16: 469947.27 | F16: 232254 | G16: 0.4942129
A17: 40575 | B17: 576737.19 | C17: 14 | D17: 534883.01 | E17: 520951.43 | F17: 55785.765 | G17: 0.10708439
A18: 40603 | B18: 758658.51 | C18: 15 | D18: 679198.99 | E18: 571955.58 | F18: 186702.93 | G18: 0.32642907
A19: 40634 | B19: 707968.04 | C19: 16 | D19: 681121.25 | E19: 622959.74 | F19: 85008.302 | G19: 0.13645874
... A21: 40695 | B21: 788024.86 | C21: 18 | D21: 774228.81 | E21: 724968.05 | F21: 63056.806 | G21: 0.086978738
A22: 40725 | B22: 906494.27 | C22: 19 | D22: 840404.22 | E22: 775972.21 | F22: 130522.06 | G22: 0.16820455 | I22: ToolPak Regression Reference
A23: 40756 | B23: 755231.15 | C23: 20 | D23: 816583.43 | E23: 826976.37 | F23: -71745.218 | G23: -0.086756068 | I23: Regression statistic | J23: Result
A24: 40787 | B24: 1205462.5 | C24: 21 | D24: 955729.3 | E24: 877980.53 | F24: 327481.95 | G24: 0.37299455 | I24: Slope | J24: 431968.3
A25: 40817 | B25: 1029973.8 | C25: 22 | D25: 996889.13 | E25: 928984.68 | F25: 100989.1 | G25: 0.10870911 | I25: Intercept | J25: -610521.8
A26: 40848 | B26: 1340417.6 | C26: 23 | D26: 1191951.3 | E26: 979988.84 | F26: 360428.74 | G26: 0.36778862 | I26: R-squared | J26: 0.87017327
A27: 40878 | B27: 245075.74 | C27: 24 | D27: 871822.37 | E27: 1030993 | F27: -785917.26 | G27: -0.76229156 | I27: p-value (slope) | J27: 0.0049517289
I28: Standard error | J28: 99860.446
A30: Significant variance rule | B30: Absolute variance vs trend >= 20% | I30: Interpretation | J30: The deseasonalized quarterly trend is statistically significant at the 5% level (p≈0.005) with R²≈0.87 in this prepared regression reference.
A33: Quarter | B33: Revenue | C33: Time Index | D33: Quarter No | E33: Seasonal Index | F33: Deseasonalized | G33: Trend
A34: 2010Q1 | B34: 153652.88 | C34: 1 | D34: 1 | E34: 0.82171732 | F34: 186989.95 | G34: -178553.5
A35: 2010Q2 | B35: 86605.41 | C35: 2 | D35: 2 | E35: 0.90348293 | F35: 95857.273 | G35: 253414.81
A36: 2010Q3 | B36: 198594.36 | C36: 3 | D36: 3 | E36: 1.1496664 | F36: 172740.85 | G36: 685383.11
A37: 2010Q4 | B37: 384893.49 | C37: 4 | D37: 4 | E37: 1.1251333 | F37: 342087 | G37: 1117351.4
A38: 2011Q1 | B38: 2037597 | C38: 5 | D38: 1 | E38: 0.82171732 | F38: 2479681.2 | G38: 1549319.7
A39: 2011Q2 | B39: 2322686.4 | C39: 6 | D39: 2 | E39: 0.90348293 | F39: 2570813.9 | G39: 1981288
A40: 2011Q3 | B40: 2867187.9 | C40: 7 | D40: 3 | E40: 1.1496664 | F40: 2493930.3 | G40: 2413256.3
A41: 2011Q4 | B41: 2615467.1 | C41: 8 | D41: 4 | E41: 1.1251333 | F41: 2324584.1 | G41: 2845224.6

Sheet Submission_Notes
A1: Submission / Refresh Notes
A2: Source file | B2: OnlineRetail_Raw_Source.xlsx is the exact uploaded 541,909-row source workbook.
A3: Task 1 | B3: Power Query M code is on Data_Profile. Replace <PATH_TO_OnlineRetail_Raw_Source.xlsx> with the actual file path, then Data → Get Data → From Other Sources → Blank Query → Advanced Editor.
A4: Task 2 | B4: Hourly_Pivot_AOV is a Pivot-style analytical table. AOV = Revenue / Orders. Revenue per Minute = Revenue / 60. Review flag uses above-median Orders/Minute + below-median AOV.
A5: Task 3 | B5: Pareto_Analysis uses a 20% threshold cell. Cumulative Revenue and Cumulative % are formula-driven. Change B3 from 20% to another threshold to update the top-count logic.
A6: Task 4 | B6: TimeSeries_Forecast contains monthly revenue, 3M moving average, trend and variance. The forecast formula uses FORECAST.LINEAR on deseasonalized quarterly revenue multiplied by the Q1 seasonal index.
A7: Important | B7: A true conversion rate cannot be calculated from this dataset because there is no sessions/visits field.
A8: Important | B8: Profit-margin dilution cannot be proven because the dataset has no product cost/profit field.
A9: Excel ToolPak | B9: If your instructor checks the ToolPak step, enable Analysis ToolPak via File → Options → Add-ins → Excel Add-ins → Go → Analysis ToolPak. Then reproduce the regression using the quarterly table.
A10: Submission | B10: Submit both Excel files together if the portal accepts multiple files. If it accepts only one file, submit OnlineRetail_Advanced_Analysis.xlsx and include the source workbook in the same GitHub/Drive repository.
